[
    {
        "occupation": "Chemist",
        "symbol": "C",
        "type": "TRADER",
        "personality": "Nervous and excitable, speaks in breathless run-on sentences about reagents and reactions. Prone to accidental self-poisoning. Fiercely proud of their potions.",
        "potential_sales": [
            { "item": "Weak Healing Potion", "chance": 100 },
            { "item": "Medium Healing Potion", "chance": 100 },
            { "item": "Strong Healing Potion", "chance": 60 },
            { "item": "Scroll of Teleportation", "chance": 40 }
        ]
    },
    {
        "occupation": "Blacksmith",
        "symbol": "B",
        "type": "TRADER",
        "personality": "Gruff, laconic, and proud of their craft. Speaks in short sentences. Distrusts magic and magic-users. Judges adventurers by the quality of their equipment.",
        "potential_sales": [
            { "item": "Club", "chance": 100 },
            { "item": "Dagger", "chance": 100 },
            { "item": "Whip", "chance": 85 },
            { "item": "Rapier", "chance": 75 },
            { "item": "Quick Blade", "chance": 30 },
            { "item": "Short Sword", "chance": 80 },
            { "item": "Scimitar", "chance": 65 },
            { "item": "Hand Axe", "chance": 70 },
            { "item": "Mace", "chance": 70 },
            { "item": "Flail", "chance": 55 },
            { "item": "Spear", "chance": 60 },
            { "item": "Trident", "chance": 55 },
            { "item": "Demon Trident", "chance": 15 },
            { "item": "Morningstar", "chance": 45 },
            { "item": "Falchion", "chance": 40 },
            { "item": "Dire Flail", "chance": 30 },
            { "item": "Broad Axe", "chance": 35 },
            { "item": "Demon Blade", "chance": 12 },
            { "item": "Eveningstar", "chance": 25 },
            { "item": "Sacred Scourge", "chance": 18 },
            { "item": "Long Sword", "chance": 40 },
            { "item": "Eudemon Blade", "chance": 8 },
            { "item": "Trishula", "chance": 10 },
            { "item": "Demon Whip", "chance": 6 },
            { "item": "Double Sword", "chance": 6 },
            { "item": "Halberd", "chance": 20 },
            { "item": "Battleaxe", "chance": 18 },
            { "item": "Great Sword", "chance": 15 },
            { "item": "Partisan", "chance": 10 },
            { "item": "Glaive", "chance": 12 },
            { "item": "War Axe", "chance": 25 },
            { "item": "Great Mace", "chance": 10 },
            { "item": "Giant Club", "chance": 6 },
            { "item": "Bardiche", "chance": 5 },
            { "item": "Triple Sword", "chance": 4 },
            { "item": "Giant Spiked Club", "chance": 4 },
            { "item": "Executioner's Axe", "chance": 5 },
            { "item": "Robe", "chance": 80 },
            { "item": "Leather Armour", "chance": 80 },
            { "item": "Ring Mail", "chance": 60 },
            { "item": "Scale Mail", "chance": 50 },
            { "item": "Chain Mail", "chance": 40 },
            { "item": "Plate Armour", "chance": 20 },
            { "item": "Crystal Plate Armour", "chance": 5 },
            { "item": "Buckler", "chance": 60 },
            { "item": "Kite Shield", "chance": 40 },
            { "item": "Tower Shield", "chance": 15 },
            { "item": "Hat", "chance": 70 },
            { "item": "Helmet", "chance": 60 },
            { "item": "Scarf", "chance": 70 },
            { "item": "Cloak", "chance": 60 },
            { "item": "Gloves", "chance": 60 },
            { "item": "Boots", "chance": 60 }
        ]
    },
    {
        "occupation": "Fletcher",
        "symbol": "F",
        "type": "TRADER",
        "personality": "Quiet and precise, talks more to their bowstrings than to people. Tests every shaft for true flight before it leaves their stall.",
        "potential_sales": [
            { "item": "Sling", "chance": 100 },
            { "item": "Hand Crossbow", "chance": 80 },
            { "item": "Short Bow", "chance": 70 },
            { "item": "Orcbow", "chance": 25 },
            { "item": "Long Bow", "chance": 35 },
            { "item": "Crossbow", "chance": 30 },
            { "item": "Arbalest", "chance": 15 },
            { "item": "Hand Cannon", "chance": 8 },
            { "item": "Triple Crossbow", "chance": 4 },
            { "item": "Stone", "chance": 90 },
            { "item": "Dart", "chance": 90 },
            { "item": "Boomerang", "chance": 55 },
            { "item": "Javelin", "chance": 45 },
            { "item": "Large Rock", "chance": 25 }
        ]
    },
    {
        "occupation": "Merchant",
        "symbol": "M",
        "type": "TRADER",
        "personality": "Sly, flattering, and always angling for a better deal. Uses flowery language and vague promises. Hides their anxiety about being this deep underground behind a merchant's smile.",
        "potential_sales": [
            { "item": "Medium Healing Potion", "chance": 80 },
            { "item": "Scroll of Magic Mapping", "chance": 70 },
            { "item": "Scroll of Teleportation", "chance": 60 },
            { "item": "Scroll of Identification", "chance": 70 },
            { "item": "Cloth Bag", "chance": 60 },
            { "item": "Leather Pack", "chance": 30 },
            { "item": "Magical Staff", "chance": 55 },
            { "item": "Quarterstaff", "chance": 40 },
            { "item": "Staff of Earth", "chance": 30 },
            { "item": "Staff of Flame", "chance": 25 },
            { "item": "Staff of Frost", "chance": 25 },
            { "item": "Staff of Venom", "chance": 25 },
            { "item": "Staff of Lightning", "chance": 20 },
            { "item": "Lajatang", "chance": 12 }
        ]
    },
    {
        "occupation": "Healer",
        "symbol": "H",
        "type": "HEALER",
        "personality": "Serene and unhurried, speaks softly and never wastes words. Has seen too much death to be surprised by anything. Quietly disapproves of unnecessary violence.",
        "heal_cost_per_hp": 2
    }
]
